{
  "$schema": "../../schemas/place.schema.json",
  "slug": "konjiam",
  "name": "Konjiam",
  "region": "South Korea",
  "country": "KR",
  "coordinates": {
    "latitude": 37.33691985016501,
    "longitude": 127.29351991528104
  },
  "elevations": {
    "base_m": 0,
    "summit_m": 0
  },
  "tags": [
    "resort",
    "korea"
  ],
  "links": {
    "homepage": "https://www.konjiamresort.co.kr/main.dev",
    "weather": "https://www.weather.go.kr/w/index.do#dong/4146125300/37.33691985016501/127.29351991528104/"
  },
  "names": {
    "ko": "곤지암",
    "en": "Konjiam",
    "ja": "ゴンジアム"
  },
  "stats": {
    "run_count": 10,
    "lift_count": 5,
    "webcam_count": 5
  },
  "source": {
    "seed": "paulkim-xr/SkiWatch"
  }
}
